[
    {
        "data": {
            "recordPageView": {
                "__typename": "PageViewSummary",
                "totalCount": 131
            }
        }
    },
    {
        "data": {
            "employerReviews": {
                "__typename": "EmployerReviewsRG",
                "allReviewsCount": 5923,
                "currentPage": 130,
                "filteredReviewsCount": 4303,
                "lastReviewDateTime": "2025-04-16T19:49:30.097",
                "numberOfPages": 431,
                "queryJobTitle": null,
                "queryLocation": null,
                "ratedReviewsCount": 4826,
                "ratingCountDistribution": {
                    "__typename": "RatingCountDistribution",
                    "careerOpportunities": {
                        "_1": 687,
                        "_2": 624,
                        "_3": 953,
                        "_4": 951,
                        "_5": 849,
                        "__typename": "FiveStarRatingCountDistribution"
                    },
                    "compensationAndBenefits": {
                        "_1": 861,
                        "_2": 854,
                        "_3": 1134,
                        "_4": 764,
                        "_5": 439,
                        "__typename": "FiveStarRatingCountDistribution"
                    },
                    "cultureAndValues": {
                        "_1": 550,
                        "_2": 382,
                        "_3": 680,
                        "_4": 875,
                        "_5": 1508,
                        "__typename": "FiveStarRatingCountDistribution"
                    },
                    "diversityAndInclusion": {
                        "_1": 239,
                        "_2": 141,
                        "_3": 320,
                        "_4": 474,
                        "_5": 754,
                        "__typename": "FiveStarRatingCountDistribution"
                    },
                    "overall": {
                        "_1": 593,
                        "_2": 616,
                        "_3": 1129,
                        "_4": 1369,
                        "_5": 1105,
                        "__typename": "FiveStarRatingCountDistribution"
                    },
                    "recommendToFriend": {
                        "RECOMMEND": 2123,
                        "WONT_RECOMMEND": 1390,
                        "__typename": "RecommendToFriendRatingCountDistribution"
                    },
                    "seniorManagement": {
                        "_1": 879,
                        "_2": 589,
                        "_3": 852,
                        "_4": 888,
                        "_5": 763,
                        "__typename": "FiveStarRatingCountDistribution"
                    },
                    "workLifeBalance": {
                        "_1": 768,
                        "_2": 624,
                        "_3": 898,
                        "_4": 900,
                        "_5": 853,
                        "__typename": "FiveStarRatingCountDistribution"
                    }
                },
                "ratings": {
                    "__typename": "EmployerRatings",
                    "businessOutlookRating": 0.49,
                    "careerOpportunitiesRating": 3.2,
                    "ceoRating": 0.69,
                    "compensationAndBenefitsRating": 2.9,
                    "cultureAndValuesRating": 3.6,
                    "diversityAndInclusionRating": 3.8,
                    "overallRating": 3.4,
                    "ratedCeo": {
                        "__typename": "Ceo",
                        "id": 250182,
                        "largePhoto": "https://media.glassdoor.com/people/sqll/335551/ef-education-first-ceo1648550297076.png",
                        "name": "Edward Hult, Ph.D",
                        "regularPhoto": "https://media.glassdoor.com/people/sql/335551/ef-education-first-ceo1648550297076.png",
                        "title": "CEO "
                    },
                    "recommendToFriendRating": 0.61,
                    "reviewCount": 4817,
                    "seniorManagementRating": 3.1,
                    "workLifeBalanceRating": 3.2
                },
                "reviews": [
                    {
                        "__typename": "EmployerReviewRG",
                        "advice": "Pay more to hard working, high performing employees",
                        "adviceOriginal": null,
                        "cons": "Low pay, education isn't important even if it's relevant",
                        "consOriginal": null,
                        "countHelpful": 0,
                        "countNotHelpful": 0,
                        "employer": {
                            "__typename": "Employer",
                            "id": 335551,
                            "largeLogoUrl": "https://media.glassdoor.com/sqll/335551/ef-education-first-squareLogo-1731701655267.png",
                            "regularLogoUrl": "https://media.glassdoor.com/sql/335551/ef-education-first-squareLogo-1731701654832.png",
                            "shortName": "EF Education First"
                        },
                        "employerResponses": [
                            {
                                "__typename": "EmployerResponse",
                                "countHelpful": 0,
                                "countNotHelpful": 0,
                                "id": 2575470,
                                "languageId": "eng",
                                "originalLanguageId": null,
                                "response": "Thank you for this feedback! We certainly agree that our colleagues at EF are very special people and we are very proud of our strong company culture. In terms of salary, we do review our compensation structure regularly to ensure we are offering a competitive package. We wish you all the best in your future endeavors.",
                                "responseDateTime": "2020-03-30T06:01:25.883",
                                "responseOriginal": null,
                                "translationMethod": null
                            }
                        ],
                        "employmentStatus": "REGULAR",
                        "featured": false,
                        "flaggingDisabled": null,
                        "isCurrentJob": false,
                        "jobTitle": {
                            "__typename": "JobTitle",
                            "id": 32050,
                            "text": "English Teacher"
                        },
                        "languageId": "eng",
                        "lengthOfEmployment": 2,
                        "location": {
                            "__typename": "City",
                            "id": 1147473,
                            "name": "Santa Barbara, CA",
                            "type": "CITY"
                        },
                        "originalLanguageId": null,
                        "pros": "Amazing, helpful coworkers, great benefits, time off",
                        "prosOriginal": null,
                        "ratingBusinessOutlook": "POSITIVE",
                        "ratingCareerOpportunities": 1.0,
                        "ratingCeo": "NO_OPINION",
                        "ratingCompensationAndBenefits": 3.0,
                        "ratingCultureAndValues": 5,
                        "ratingDiversityAndInclusion": 0,
                        "ratingOverall": 4,
                        "ratingRecommendToFriend": "POSITIVE",
                        "ratingSeniorLeadership": 3.0,
                        "ratingWorkLifeBalance": 2.0,
                        "relatedStructures": [],
                        "reviewDateTime": "2020-03-24T11:34:49.067",
                        "reviewId": 32473465,
                        "summary": "Pretty good place",
                        "summaryOriginal": null,
                        "translationMethod": null
                    },
                    {
                        "__typename": "EmployerReviewRG",
                        "advice": null,
                        "adviceOriginal": null,
                        "cons": "Not great not for long-term. People leave very quickly",
                        "consOriginal": null,
                        "countHelpful": 1,
                        "countNotHelpful": 0,
                        "employer": {
                            "__typename": "Employer",
                            "id": 335551,
                            "largeLogoUrl": "https://media.glassdoor.com/sqll/335551/ef-education-first-squareLogo-1731701655267.png",
                            "regularLogoUrl": "https://media.glassdoor.com/sql/335551/ef-education-first-squareLogo-1731701654832.png",
                            "shortName": "EF Education First"
                        },
                        "employerResponses": [],
                        "employmentStatus": "REGULAR",
                        "featured": false,
                        "flaggingDisabled": null,
                        "isCurrentJob": false,
                        "jobTitle": null,
                        "languageId": "eng",
                        "lengthOfEmployment": 6,
                        "location": {
                            "__typename": "City",
                            "id": 1154545,
                            "name": "Cambridge, MA",
                            "type": "CITY"
                        },
                        "originalLanguageId": null,
                        "pros": "It is good to start out your career here.",
                        "prosOriginal": null,
                        "ratingBusinessOutlook": null,
                        "ratingCareerOpportunities": 0.0,
                        "ratingCeo": null,
                        "ratingCompensationAndBenefits": 0.0,
                        "ratingCultureAndValues": 0,
                        "ratingDiversityAndInclusion": 0,
                        "ratingOverall": 4,
                        "ratingRecommendToFriend": null,
                        "ratingSeniorLeadership": 0.0,
                        "ratingWorkLifeBalance": 0.0,
                        "relatedStructures": [],
                        "reviewDateTime": "2020-08-19T08:05:40.427",
                        "reviewId": 35065373,
                        "summary": "Great company to start out",
                        "summaryOriginal": null,
                        "translationMethod": null
                    },
                    {
                        "__typename": "EmployerReviewRG",
                        "advice": "match salaries to Boston standards",
                        "adviceOriginal": null,
                        "cons": "extremely low pay, poor management, growth only for a few select staffers",
                        "consOriginal": null,
                        "countHelpful": 0,
                        "countNotHelpful": 0,
                        "employer": {
                            "__typename": "Employer",
                            "id": 335551,
                            "largeLogoUrl": "https://media.glassdoor.com/sqll/335551/ef-education-first-squareLogo-1731701655267.png",
                            "regularLogoUrl": "https://media.glassdoor.com/sql/335551/ef-education-first-squareLogo-1731701654832.png",
                            "shortName": "EF Education First"
                        },
                        "employerResponses": [],
                        "employmentStatus": "REGULAR",
                        "featured": false,
                        "flaggingDisabled": null,
                        "isCurrentJob": false,
                        "jobTitle": {
                            "__typename": "JobTitle",
                            "id": 61502,
                            "text": "Program Manager"
                        },
                        "languageId": "eng",
                        "lengthOfEmployment": 6,
                        "location": {
                            "__typename": "City",
                            "id": 1154545,
                            "name": "Cambridge, MA",
                            "type": "CITY"
                        },
                        "originalLanguageId": null,
                        "pros": "Travel Opportunities, amazing coworkers, mission driven work",
                        "prosOriginal": null,
                        "ratingBusinessOutlook": null,
                        "ratingCareerOpportunities": 0.0,
                        "ratingCeo": null,
                        "ratingCompensationAndBenefits": 0.0,
                        "ratingCultureAndValues": 0,
                        "ratingDiversityAndInclusion": 0,
                        "ratingOverall": 3,
                        "ratingRecommendToFriend": null,
                        "ratingSeniorLeadership": 0.0,
                        "ratingWorkLifeBalance": 0.0,
                        "relatedStructures": [],
                        "reviewDateTime": "2021-01-14T12:08:36.553",
                        "reviewId": 40716760,
                        "summary": "Great Coworkers, Poor Pay",
                        "summaryOriginal": null,
                        "translationMethod": null
                    },
                    {
                        "__typename": "EmployerReviewRG",
                        "advice": null,
                        "adviceOriginal": null,
                        "cons": "Salary isn't competitive; not a lot of upward mobility",
                        "consOriginal": null,
                        "countHelpful": 0,
                        "countNotHelpful": 0,
                        "employer": {
                            "__typename": "Employer",
                            "id": 335551,
                            "largeLogoUrl": "https://media.glassdoor.com/sqll/335551/ef-education-first-squareLogo-1731701655267.png",
                            "regularLogoUrl": "https://media.glassdoor.com/sql/335551/ef-education-first-squareLogo-1731701654832.png",
                            "shortName": "EF Education First"
                        },
                        "employerResponses": [],
                        "employmentStatus": "REGULAR",
                        "featured": false,
                        "flaggingDisabled": null,
                        "isCurrentJob": true,
                        "jobTitle": {
                            "__typename": "JobTitle",
                            "id": 28495,
                            "text": "Sales Manager"
                        },
                        "languageId": "eng",
                        "lengthOfEmployment": 0,
                        "location": {
                            "__typename": "City",
                            "id": 1154532,
                            "name": "Boston, MA",
                            "type": "CITY"
                        },
                        "originalLanguageId": null,
                        "pros": "Travel; amazing work culture; great professional development for young professionals",
                        "prosOriginal": null,
                        "ratingBusinessOutlook": "POSITIVE",
                        "ratingCareerOpportunities": 3.0,
                        "ratingCeo": "APPROVE",
                        "ratingCompensationAndBenefits": 2.0,
                        "ratingCultureAndValues": 5,
                        "ratingDiversityAndInclusion": 3,
                        "ratingOverall": 4,
                        "ratingRecommendToFriend": "POSITIVE",
                        "ratingSeniorLeadership": 3.0,
                        "ratingWorkLifeBalance": 3.0,
                        "relatedStructures": [],
                        "reviewDateTime": "2021-01-15T07:15:05.697",
                        "reviewId": 40770562,
                        "summary": "Great place to start and grow your career",
                        "summaryOriginal": null,
                        "translationMethod": null
                    },
                    {
                        "__typename": "EmployerReviewRG",
                        "advice": null,
                        "adviceOriginal": null,
                        "cons": "low salary and no price negotiation for starting salary",
                        "consOriginal": null,
                        "countHelpful": 0,
                        "countNotHelpful": 0,
                        "employer": {
                            "__typename": "Employer",
                            "id": 335551,
                            "largeLogoUrl": "https://media.glassdoor.com/sqll/335551/ef-education-first-squareLogo-1731701655267.png",
                            "regularLogoUrl": "https://media.glassdoor.com/sql/335551/ef-education-first-squareLogo-1731701654832.png",
                            "shortName": "EF Education First"
                        },
                        "employerResponses": [],
                        "employmentStatus": "REGULAR",
                        "featured": false,
                        "flaggingDisabled": null,
                        "isCurrentJob": true,
                        "jobTitle": null,
                        "languageId": "eng",
                        "lengthOfEmployment": 0,
                        "location": null,
                        "originalLanguageId": null,
                        "pros": "PD opportunities as a new employee, and within your first two years at EF",
                        "prosOriginal": null,
                        "ratingBusinessOutlook": null,
                        "ratingCareerOpportunities": 4.0,
                        "ratingCeo": null,
                        "ratingCompensationAndBenefits": 0.0,
                        "ratingCultureAndValues": 0,
                        "ratingDiversityAndInclusion": 0,
                        "ratingOverall": 4,
                        "ratingRecommendToFriend": null,
                        "ratingSeniorLeadership": 0.0,
                        "ratingWorkLifeBalance": 0.0,
                        "relatedStructures": [],
                        "reviewDateTime": "2021-05-27T09:43:17.840",
                        "reviewId": 47552021,
                        "summary": "Great professional development opportunities",
                        "summaryOriginal": null,
                        "translationMethod": null
                    },
                    {
                        "__typename": "EmployerReviewRG",
                        "advice": null,
                        "adviceOriginal": null,
                        "cons": "-Lower salary compared to Boston-bound companies \n-Not much upward movement",
                        "consOriginal": null,
                        "countHelpful": 0,
                        "countNotHelpful": 0,
                        "employer": {
                            "__typename": "Employer",
                            "id": 335551,
                            "largeLogoUrl": "https://media.glassdoor.com/sqll/335551/ef-education-first-squareLogo-1731701655267.png",
                            "regularLogoUrl": "https://media.glassdoor.com/sql/335551/ef-education-first-squareLogo-1731701654832.png",
                            "shortName": "EF Education First"
                        },
                        "employerResponses": [],
                        "employmentStatus": "REGULAR",
                        "featured": false,
                        "flaggingDisabled": null,
                        "isCurrentJob": true,
                        "jobTitle": null,
                        "languageId": "eng",
                        "lengthOfEmployment": 4,
                        "location": {
                            "__typename": "City",
                            "id": 1154545,
                            "name": "Cambridge, MA",
                            "type": "CITY"
                        },
                        "originalLanguageId": null,
                        "pros": "-Fun environment (College-like) \n-Great healthcare and other perks\n-Transfer opportunities within U.S. and abroad",
                        "prosOriginal": null,
                        "ratingBusinessOutlook": "POSITIVE",
                        "ratingCareerOpportunities": 3.0,
                        "ratingCeo": "APPROVE",
                        "ratingCompensationAndBenefits": 2.0,
                        "ratingCultureAndValues": 5,
                        "ratingDiversityAndInclusion": 3,
                        "ratingOverall": 3,
                        "ratingRecommendToFriend": "POSITIVE",
                        "ratingSeniorLeadership": 3.0,
                        "ratingWorkLifeBalance": 5.0,
                        "relatedStructures": [],
                        "reviewDateTime": "2021-08-11T13:54:00.277",
                        "reviewId": 50998369,
                        "summary": "Fun Place to Start Career",
                        "summaryOriginal": null,
                        "translationMethod": null
                    },
                    {
                        "__typename": "EmployerReviewRG",
                        "advice": null,
                        "adviceOriginal": null,
                        "cons": "Discriminatory salary policies, poor management, highly siloed, poor salary, spent money on stupid offsite meetings instead of necssities",
                        "consOriginal": null,
                        "countHelpful": 1,
                        "countNotHelpful": 0,
                        "employer": {
                            "__typename": "Employer",
                            "id": 335551,
                            "largeLogoUrl": "https://media.glassdoor.com/sqll/335551/ef-education-first-squareLogo-1731701655267.png",
                            "regularLogoUrl": "https://media.glassdoor.com/sql/335551/ef-education-first-squareLogo-1731701654832.png",
                            "shortName": "EF Education First"
                        },
                        "employerResponses": [],
                        "employmentStatus": "REGULAR",
                        "featured": false,
                        "flaggingDisabled": null,
                        "isCurrentJob": false,
                        "jobTitle": {
                            "__typename": "JobTitle",
                            "id": 35282,
                            "text": "Senior Training Manager"
                        },
                        "languageId": "eng",
                        "lengthOfEmployment": 9,
                        "location": null,
                        "originalLanguageId": null,
                        "pros": "Good colleagues, opportunities to learn",
                        "prosOriginal": null,
                        "ratingBusinessOutlook": "NEGATIVE",
                        "ratingCareerOpportunities": 4.0,
                        "ratingCeo": "DISAPPROVE",
                        "ratingCompensationAndBenefits": 1.0,
                        "ratingCultureAndValues": 2,
                        "ratingDiversityAndInclusion": 2,
                        "ratingOverall": 3,
                        "ratingRecommendToFriend": "NEGATIVE",
                        "ratingSeniorLeadership": 2.0,
                        "ratingWorkLifeBalance": 4.0,
                        "relatedStructures": [],
                        "reviewDateTime": "2021-12-15T01:23:11.997",
                        "reviewId": 56703374,
                        "summary": "Not awful",
                        "summaryOriginal": null,
                        "translationMethod": null
                    },
                    {
                        "__typename": "EmployerReviewRG",
                        "advice": null,
                        "adviceOriginal": null,
                        "cons": "Low pay and lots of lateral movement",
                        "consOriginal": null,
                        "countHelpful": 1,
                        "countNotHelpful": 0,
                        "employer": {
                            "__typename": "Employer",
                            "id": 335551,
                            "largeLogoUrl": "https://media.glassdoor.com/sqll/335551/ef-education-first-squareLogo-1731701655267.png",
                            "regularLogoUrl": "https://media.glassdoor.com/sql/335551/ef-education-first-squareLogo-1731701654832.png",
                            "shortName": "EF Education First"
                        },
                        "employerResponses": [],
                        "employmentStatus": "REGULAR",
                        "featured": false,
                        "flaggingDisabled": null,
                        "isCurrentJob": false,
                        "jobTitle": {
                            "__typename": "JobTitle",
                            "id": 247551,
                            "text": "Educational Tour Consultant"
                        },
                        "languageId": "eng",
                        "lengthOfEmployment": 4,
                        "location": {
                            "__typename": "City",
                            "id": 1154545,
                            "name": "Cambridge, MA",
                            "type": "CITY"
                        },
                        "originalLanguageId": null,
                        "pros": "Great environment, work hard, play hard mentality, tons of perks.",
                        "prosOriginal": null,
                        "ratingBusinessOutlook": null,
                        "ratingCareerOpportunities": 3.0,
                        "ratingCeo": null,
                        "ratingCompensationAndBenefits": 2.0,
                        "ratingCultureAndValues": 5,
                        "ratingDiversityAndInclusion": 5,
                        "ratingOverall": 4,
                        "ratingRecommendToFriend": "POSITIVE",
                        "ratingSeniorLeadership": 3.0,
                        "ratingWorkLifeBalance": 4.0,
                        "relatedStructures": [],
                        "reviewDateTime": "2021-12-14T20:29:07.103",
                        "reviewId": 56694788,
                        "summary": "Great place to work, low pay",
                        "summaryOriginal": null,
                        "translationMethod": null
                    },
                    {
                        "__typename": "EmployerReviewRG",
                        "advice": null,
                        "adviceOriginal": null,
                        "cons": "None that I can think of as of now.",
                        "consOriginal": null,
                        "countHelpful": 0,
                        "countNotHelpful": 0,
                        "employer": {
                            "__typename": "Employer",
                            "id": 335551,
                            "largeLogoUrl": "https://media.glassdoor.com/sqll/335551/ef-education-first-squareLogo-1731701655267.png",
                            "regularLogoUrl": "https://media.glassdoor.com/sql/335551/ef-education-first-squareLogo-1731701654832.png",
                            "shortName": "EF Education First"
                        },
                        "employerResponses": [],
                        "employmentStatus": "REGULAR",
                        "featured": false,
                        "flaggingDisabled": null,
                        "isCurrentJob": true,
                        "jobTitle": null,
                        "languageId": "eng",
                        "lengthOfEmployment": 0,
                        "location": null,
                        "originalLanguageId": null,
                        "pros": "Amazing company culture, really cares about their employees and motivates them to do their best.",
                        "prosOriginal": null,
                        "ratingBusinessOutlook": null,
                        "ratingCareerOpportunities": 4.0,
                        "ratingCeo": null,
                        "ratingCompensationAndBenefits": 5.0,
                        "ratingCultureAndValues": 5,
                        "ratingDiversityAndInclusion": 4,
                        "ratingOverall": 5,
                        "ratingRecommendToFriend": "POSITIVE",
                        "ratingSeniorLeadership": 5.0,
                        "ratingWorkLifeBalance": 5.0,
                        "relatedStructures": [],
                        "reviewDateTime": "2022-01-13T10:09:47.760",
                        "reviewId": 57875026,
                        "summary": "Amazing Company",
                        "summaryOriginal": null,
                        "translationMethod": null
                    },
                    {
                        "__typename": "EmployerReviewRG",
                        "advice": null,
                        "adviceOriginal": null,
                        "cons": "Low base pay, high turnover, tough industry during Covid",
                        "consOriginal": null,
                        "countHelpful": 0,
                        "countNotHelpful": 0,
                        "employer": {
                            "__typename": "Employer",
                            "id": 335551,
                            "largeLogoUrl": "https://media.glassdoor.com/sqll/335551/ef-education-first-squareLogo-1731701655267.png",
                            "regularLogoUrl": "https://media.glassdoor.com/sql/335551/ef-education-first-squareLogo-1731701654832.png",
                            "shortName": "EF Education First"
                        },
                        "employerResponses": [
                            {
                                "__typename": "EmployerResponse",
                                "countHelpful": 0,
                                "countNotHelpful": 0,
                                "id": 3783022,
                                "languageId": "eng",
                                "originalLanguageId": null,
                                "response": "Thank you for taking the time to leave us a review! We're happy to hear you are enjoying the company culture and the EF Boston facilities. In terms of salary, we do review our compensation structure regularly to ensure we are offering a competitive package within our industry. Thank you again for taking the time to share with us this feedback. We are happy to have you part of the EF community!",
                                "responseDateTime": "2022-02-08T07:04:27.32",
                                "responseOriginal": null,
                                "translationMethod": null
                            }
                        ],
                        "employmentStatus": "REGULAR",
                        "featured": false,
                        "flaggingDisabled": null,
                        "isCurrentJob": true,
                        "jobTitle": {
                            "__typename": "JobTitle",
                            "id": 21799,
                            "text": "Tour Consultant"
                        },
                        "languageId": "eng",
                        "lengthOfEmployment": 1,
                        "location": {
                            "__typename": "City",
                            "id": 1154532,
                            "name": "Boston, MA",
                            "type": "CITY"
                        },
                        "originalLanguageId": null,
                        "pros": "Great team spirit and team atmosphere, opportunities for commission based on performance, excellent facilities, supportive management",
                        "prosOriginal": null,
                        "ratingBusinessOutlook": null,
                        "ratingCareerOpportunities": 4.0,
                        "ratingCeo": null,
                        "ratingCompensationAndBenefits": 3.0,
                        "ratingCultureAndValues": 5,
                        "ratingDiversityAndInclusion": 5,
                        "ratingOverall": 4,
                        "ratingRecommendToFriend": "POSITIVE",
                        "ratingSeniorLeadership": 5.0,
                        "ratingWorkLifeBalance": 5.0,
                        "relatedStructures": [],
                        "reviewDateTime": "2022-02-07T18:22:08.593",
                        "reviewId": 59269381,
                        "summary": "Great Experience",
                        "summaryOriginal": null,
                        "translationMethod": null
                    }
                ]
            }
        }
    }
]