[
    {
        "data": {
            "recordPageView": {
                "__typename": "PageViewSummary",
                "totalCount": 321
            }
        }
    },
    {
        "data": {
            "employerReviews": {
                "__typename": "EmployerReviewsRG",
                "allReviewsCount": 5923,
                "currentPage": 320,
                "filteredReviewsCount": 4303,
                "lastReviewDateTime": "2025-04-16T19:49:30.097",
                "numberOfPages": 431,
                "queryJobTitle": null,
                "queryLocation": null,
                "ratedReviewsCount": 4826,
                "ratingCountDistribution": {
                    "__typename": "RatingCountDistribution",
                    "careerOpportunities": {
                        "_1": 687,
                        "_2": 624,
                        "_3": 953,
                        "_4": 951,
                        "_5": 849,
                        "__typename": "FiveStarRatingCountDistribution"
                    },
                    "compensationAndBenefits": {
                        "_1": 861,
                        "_2": 854,
                        "_3": 1134,
                        "_4": 764,
                        "_5": 439,
                        "__typename": "FiveStarRatingCountDistribution"
                    },
                    "cultureAndValues": {
                        "_1": 550,
                        "_2": 382,
                        "_3": 680,
                        "_4": 875,
                        "_5": 1508,
                        "__typename": "FiveStarRatingCountDistribution"
                    },
                    "diversityAndInclusion": {
                        "_1": 239,
                        "_2": 141,
                        "_3": 320,
                        "_4": 474,
                        "_5": 754,
                        "__typename": "FiveStarRatingCountDistribution"
                    },
                    "overall": {
                        "_1": 593,
                        "_2": 616,
                        "_3": 1129,
                        "_4": 1369,
                        "_5": 1105,
                        "__typename": "FiveStarRatingCountDistribution"
                    },
                    "recommendToFriend": {
                        "RECOMMEND": 2123,
                        "WONT_RECOMMEND": 1390,
                        "__typename": "RecommendToFriendRatingCountDistribution"
                    },
                    "seniorManagement": {
                        "_1": 879,
                        "_2": 589,
                        "_3": 852,
                        "_4": 888,
                        "_5": 763,
                        "__typename": "FiveStarRatingCountDistribution"
                    },
                    "workLifeBalance": {
                        "_1": 768,
                        "_2": 624,
                        "_3": 898,
                        "_4": 900,
                        "_5": 853,
                        "__typename": "FiveStarRatingCountDistribution"
                    }
                },
                "ratings": {
                    "__typename": "EmployerRatings",
                    "businessOutlookRating": 0.49,
                    "careerOpportunitiesRating": 3.2,
                    "ceoRating": 0.69,
                    "compensationAndBenefitsRating": 2.9,
                    "cultureAndValuesRating": 3.6,
                    "diversityAndInclusionRating": 3.8,
                    "overallRating": 3.4,
                    "ratedCeo": {
                        "__typename": "Ceo",
                        "id": 250182,
                        "largePhoto": "https://media.glassdoor.com/people/sqll/335551/ef-education-first-ceo1648550297076.png",
                        "name": "Edward Hult, Ph.D",
                        "regularPhoto": "https://media.glassdoor.com/people/sql/335551/ef-education-first-ceo1648550297076.png",
                        "title": "CEO "
                    },
                    "recommendToFriendRating": 0.61,
                    "reviewCount": 4817,
                    "seniorManagementRating": 3.1,
                    "workLifeBalanceRating": 3.2
                },
                "reviews": [
                    {
                        "__typename": "EmployerReviewRG",
                        "advice": null,
                        "adviceOriginal": null,
                        "cons": "Long hours and feeling like you need to be responsive outside of 9-5 window at times, because it's travel and that can be unpredictable :)",
                        "consOriginal": null,
                        "countHelpful": 1,
                        "countNotHelpful": 0,
                        "employer": {
                            "__typename": "Employer",
                            "id": 335551,
                            "largeLogoUrl": "https://media.glassdoor.com/sqll/335551/ef-education-first-squareLogo-1731701655267.png",
                            "regularLogoUrl": "https://media.glassdoor.com/sql/335551/ef-education-first-squareLogo-1731701654832.png",
                            "shortName": "EF Education First"
                        },
                        "employerResponses": [],
                        "employmentStatus": "REGULAR",
                        "featured": false,
                        "flaggingDisabled": null,
                        "isCurrentJob": false,
                        "jobTitle": null,
                        "languageId": "eng",
                        "lengthOfEmployment": 0,
                        "location": null,
                        "originalLanguageId": null,
                        "pros": "Free travel, beer fridge, fun environment with lovely people looking to open up the world through educational travel.",
                        "prosOriginal": null,
                        "ratingBusinessOutlook": null,
                        "ratingCareerOpportunities": 0.0,
                        "ratingCeo": null,
                        "ratingCompensationAndBenefits": 0.0,
                        "ratingCultureAndValues": 0,
                        "ratingDiversityAndInclusion": 0,
                        "ratingOverall": 4,
                        "ratingRecommendToFriend": null,
                        "ratingSeniorLeadership": 0.0,
                        "ratingWorkLifeBalance": 0.0,
                        "relatedStructures": [],
                        "reviewDateTime": "2021-08-20T06:23:12.277",
                        "reviewId": 51388290,
                        "summary": "Great!",
                        "summaryOriginal": null,
                        "translationMethod": null
                    },
                    {
                        "__typename": "EmployerReviewRG",
                        "advice": "Embrace experienced employees and help them spread this experience and be able to work remotely, train new managers to be great and inspirational leaders, modernize systems and create a true HR organization.",
                        "adviceOriginal": null,
                        "cons": "Advancement opportunities non-existent if you don't want to move",
                        "consOriginal": null,
                        "countHelpful": 0,
                        "countNotHelpful": 0,
                        "employer": {
                            "__typename": "Employer",
                            "id": 335551,
                            "largeLogoUrl": "https://media.glassdoor.com/sqll/335551/ef-education-first-squareLogo-1731701655267.png",
                            "regularLogoUrl": "https://media.glassdoor.com/sql/335551/ef-education-first-squareLogo-1731701654832.png",
                            "shortName": "EF Education First"
                        },
                        "employerResponses": [
                            {
                                "__typename": "EmployerResponse",
                                "countHelpful": 0,
                                "countNotHelpful": 0,
                                "id": 4025192,
                                "languageId": "eng",
                                "originalLanguageId": null,
                                "response": "Thank you for writing a review and for your tenure with us! It is great to hear that the entrepreneurial environment has kept you with us for over 20 years. As we continue to look ahead and strategize how to best support our team members, we are certainly having conversations about what that looks like at EF. Feedback like yours is important in these discussions, so we thank you for sharing. If you'd like to share more, we'd encourage you to reach out to us at HR@ef.com. We hope you can continue to grow with us!",
                                "responseDateTime": "2022-05-31T21:48:40.437",
                                "responseOriginal": null,
                                "translationMethod": null
                            }
                        ],
                        "employmentStatus": "REGULAR",
                        "featured": false,
                        "flaggingDisabled": null,
                        "isCurrentJob": true,
                        "jobTitle": null,
                        "languageId": "eng",
                        "lengthOfEmployment": 20,
                        "location": null,
                        "originalLanguageId": null,
                        "pros": "entrepreneurial possibilities, great company for young people",
                        "prosOriginal": null,
                        "ratingBusinessOutlook": "POSITIVE",
                        "ratingCareerOpportunities": 1.0,
                        "ratingCeo": null,
                        "ratingCompensationAndBenefits": 1.0,
                        "ratingCultureAndValues": 5,
                        "ratingDiversityAndInclusion": 1,
                        "ratingOverall": 3,
                        "ratingRecommendToFriend": "POSITIVE",
                        "ratingSeniorLeadership": 1.0,
                        "ratingWorkLifeBalance": 5.0,
                        "relatedStructures": [],
                        "reviewDateTime": "2022-05-30T09:02:49.570",
                        "reviewId": 64857276,
                        "summary": "EF",
                        "summaryOriginal": null,
                        "translationMethod": null
                    },
                    {
                        "__typename": "EmployerReviewRG",
                        "advice": null,
                        "adviceOriginal": null,
                        "cons": "Little work-life balance\nLow salary\nLow employee retention\nSometimes there is overtime without any extra pay\nAt times many mundane routine tasks",
                        "consOriginal": null,
                        "countHelpful": 2,
                        "countNotHelpful": 0,
                        "employer": {
                            "__typename": "Employer",
                            "id": 335551,
                            "largeLogoUrl": "https://media.glassdoor.com/sqll/335551/ef-education-first-squareLogo-1731701655267.png",
                            "regularLogoUrl": "https://media.glassdoor.com/sql/335551/ef-education-first-squareLogo-1731701654832.png",
                            "shortName": "EF Education First"
                        },
                        "employerResponses": [],
                        "employmentStatus": "REGULAR",
                        "featured": false,
                        "flaggingDisabled": null,
                        "isCurrentJob": true,
                        "jobTitle": {
                            "__typename": "JobTitle",
                            "id": 50776,
                            "text": "Sales and Marketing Coordinator"
                        },
                        "languageId": "eng",
                        "lengthOfEmployment": 2,
                        "location": {
                            "__typename": "City",
                            "id": 2918317,
                            "name": "Oslo",
                            "type": "CITY"
                        },
                        "originalLanguageId": null,
                        "pros": "International workplace, contact with people in many different countries\nEnglish working language\nTravels \nExperience in many areas\nGood vacation policy",
                        "prosOriginal": null,
                        "ratingBusinessOutlook": "POSITIVE",
                        "ratingCareerOpportunities": 4.0,
                        "ratingCeo": "NO_OPINION",
                        "ratingCompensationAndBenefits": 2.0,
                        "ratingCultureAndValues": 4,
                        "ratingDiversityAndInclusion": 0,
                        "ratingOverall": 3,
                        "ratingRecommendToFriend": "NEGATIVE",
                        "ratingSeniorLeadership": 2.0,
                        "ratingWorkLifeBalance": 2.0,
                        "relatedStructures": [],
                        "reviewDateTime": "2015-07-20T18:09:25.070",
                        "reviewId": 7290939,
                        "summary": "Great experience for further career in marketing",
                        "summaryOriginal": null,
                        "translationMethod": null
                    },
                    {
                        "__typename": "EmployerReviewRG",
                        "advice": null,
                        "adviceOriginal": null,
                        "cons": "Same \"cons\" as with any high demanding employer. Partly stressful deadlines and high expectations on all output.",
                        "consOriginal": null,
                        "countHelpful": 2,
                        "countNotHelpful": 0,
                        "employer": {
                            "__typename": "Employer",
                            "id": 335551,
                            "largeLogoUrl": "https://media.glassdoor.com/sqll/335551/ef-education-first-squareLogo-1731701655267.png",
                            "regularLogoUrl": "https://media.glassdoor.com/sql/335551/ef-education-first-squareLogo-1731701654832.png",
                            "shortName": "EF Education First"
                        },
                        "employerResponses": [],
                        "employmentStatus": null,
                        "featured": false,
                        "flaggingDisabled": null,
                        "isCurrentJob": true,
                        "jobTitle": {
                            "__typename": "JobTitle",
                            "id": 1199050,
                            "text": "Global Finance Trainee"
                        },
                        "languageId": "eng",
                        "lengthOfEmployment": 0,
                        "location": null,
                        "originalLanguageId": null,
                        "pros": "The amazing company culture, spirit of entrepreneurship and freedom to run your own projects and ideas.",
                        "prosOriginal": null,
                        "ratingBusinessOutlook": "POSITIVE",
                        "ratingCareerOpportunities": 5.0,
                        "ratingCeo": "NO_OPINION",
                        "ratingCompensationAndBenefits": 4.0,
                        "ratingCultureAndValues": 5,
                        "ratingDiversityAndInclusion": 0,
                        "ratingOverall": 5,
                        "ratingRecommendToFriend": "POSITIVE",
                        "ratingSeniorLeadership": 5.0,
                        "ratingWorkLifeBalance": 5.0,
                        "relatedStructures": [],
                        "reviewDateTime": "2015-11-24T19:32:54.593",
                        "reviewId": 8742687,
                        "summary": "Global Finance Trainee",
                        "summaryOriginal": null,
                        "translationMethod": null
                    },
                    {
                        "__typename": "EmployerReviewRG",
                        "advice": "Empower your employees.",
                        "adviceOriginal": null,
                        "cons": "Low salary but a high level of responsibility and workload. High level of bureaucracy, changes take a lot of time to implement.",
                        "consOriginal": null,
                        "countHelpful": 0,
                        "countNotHelpful": 0,
                        "employer": {
                            "__typename": "Employer",
                            "id": 335551,
                            "largeLogoUrl": "https://media.glassdoor.com/sqll/335551/ef-education-first-squareLogo-1731701655267.png",
                            "regularLogoUrl": "https://media.glassdoor.com/sql/335551/ef-education-first-squareLogo-1731701654832.png",
                            "shortName": "EF Education First"
                        },
                        "employerResponses": [],
                        "employmentStatus": "REGULAR",
                        "featured": false,
                        "flaggingDisabled": null,
                        "isCurrentJob": true,
                        "jobTitle": {
                            "__typename": "JobTitle",
                            "id": 63697,
                            "text": "Manager"
                        },
                        "languageId": "eng",
                        "lengthOfEmployment": 20,
                        "location": {
                            "__typename": "City",
                            "id": 2416009,
                            "name": "Shanghai, Shanghai",
                            "type": "CITY"
                        },
                        "originalLanguageId": null,
                        "pros": "Employees are given a lot of opportunity to learn new things and grow within the company. Very strong corporate culture, good vibe.",
                        "prosOriginal": null,
                        "ratingBusinessOutlook": "NEUTRAL",
                        "ratingCareerOpportunities": 3.0,
                        "ratingCeo": "NO_OPINION",
                        "ratingCompensationAndBenefits": 1.0,
                        "ratingCultureAndValues": 5,
                        "ratingDiversityAndInclusion": 0,
                        "ratingOverall": 3,
                        "ratingRecommendToFriend": "POSITIVE",
                        "ratingSeniorLeadership": 3.0,
                        "ratingWorkLifeBalance": 2.0,
                        "relatedStructures": [],
                        "reviewDateTime": "2016-09-24T09:24:58.230",
                        "reviewId": 12057571,
                        "summary": "Manager",
                        "summaryOriginal": null,
                        "translationMethod": null
                    },
                    {
                        "__typename": "EmployerReviewRG",
                        "advice": null,
                        "adviceOriginal": null,
                        "cons": "The work hours vary from season to season so full-time employment begins after a certain time of experience",
                        "consOriginal": null,
                        "countHelpful": 0,
                        "countNotHelpful": 0,
                        "employer": {
                            "__typename": "Employer",
                            "id": 335551,
                            "largeLogoUrl": "https://media.glassdoor.com/sqll/335551/ef-education-first-squareLogo-1731701655267.png",
                            "regularLogoUrl": "https://media.glassdoor.com/sql/335551/ef-education-first-squareLogo-1731701654832.png",
                            "shortName": "EF Education First"
                        },
                        "employerResponses": [],
                        "employmentStatus": "PART_TIME",
                        "featured": false,
                        "flaggingDisabled": null,
                        "isCurrentJob": true,
                        "jobTitle": {
                            "__typename": "JobTitle",
                            "id": 42779,
                            "text": "ESL Teacher"
                        },
                        "languageId": "eng",
                        "lengthOfEmployment": 1,
                        "location": {
                            "__typename": "City",
                            "id": 2281069,
                            "name": "Toronto, ON",
                            "type": "CITY"
                        },
                        "originalLanguageId": null,
                        "pros": "The Private Language School experience here is a very interactive and creative one. People from all over the world come to learn english and experience Canada.",
                        "prosOriginal": null,
                        "ratingBusinessOutlook": "POSITIVE",
                        "ratingCareerOpportunities": 5.0,
                        "ratingCeo": "APPROVE",
                        "ratingCompensationAndBenefits": 5.0,
                        "ratingCultureAndValues": 5,
                        "ratingDiversityAndInclusion": 0,
                        "ratingOverall": 5,
                        "ratingRecommendToFriend": "POSITIVE",
                        "ratingSeniorLeadership": 5.0,
                        "ratingWorkLifeBalance": 5.0,
                        "relatedStructures": [],
                        "reviewDateTime": "2017-06-10T14:18:21.993",
                        "reviewId": 15420480,
                        "summary": "ESL Teacher",
                        "summaryOriginal": null,
                        "translationMethod": null
                    },
                    {
                        "__typename": "EmployerReviewRG",
                        "advice": "Somehow all the good team mangers keep leaving.",
                        "adviceOriginal": null,
                        "cons": "Salary not always commensurate to effort/contribution. Cliques can be exclusive and toxic, unregulated at various levels of management.",
                        "consOriginal": null,
                        "countHelpful": 0,
                        "countNotHelpful": 0,
                        "employer": {
                            "__typename": "Employer",
                            "id": 335551,
                            "largeLogoUrl": "https://media.glassdoor.com/sqll/335551/ef-education-first-squareLogo-1731701655267.png",
                            "regularLogoUrl": "https://media.glassdoor.com/sql/335551/ef-education-first-squareLogo-1731701654832.png",
                            "shortName": "EF Education First"
                        },
                        "employerResponses": [],
                        "employmentStatus": "REGULAR",
                        "featured": false,
                        "flaggingDisabled": null,
                        "isCurrentJob": false,
                        "jobTitle": null,
                        "languageId": "eng",
                        "lengthOfEmployment": 4,
                        "location": null,
                        "originalLanguageId": null,
                        "pros": "Fast moving, exciting and good if you enjoy constantly problem-solving. strong team culture. Freedom for teams to activate on projects.",
                        "prosOriginal": null,
                        "ratingBusinessOutlook": null,
                        "ratingCareerOpportunities": 3.0,
                        "ratingCeo": null,
                        "ratingCompensationAndBenefits": 2.0,
                        "ratingCultureAndValues": 2,
                        "ratingDiversityAndInclusion": 0,
                        "ratingOverall": 3,
                        "ratingRecommendToFriend": null,
                        "ratingSeniorLeadership": 2.0,
                        "ratingWorkLifeBalance": 2.0,
                        "relatedStructures": [],
                        "reviewDateTime": "2018-01-29T20:10:51.270",
                        "reviewId": 18978843,
                        "summary": "Corporate startup",
                        "summaryOriginal": null,
                        "translationMethod": null
                    },
                    {
                        "__typename": "EmployerReviewRG",
                        "advice": "None",
                        "adviceOriginal": null,
                        "cons": "I have nothing bad to say as I really enjoyed but maybe if I want to be picky I would",
                        "consOriginal": null,
                        "countHelpful": 0,
                        "countNotHelpful": 0,
                        "employer": {
                            "__typename": "Employer",
                            "id": 335551,
                            "largeLogoUrl": "https://media.glassdoor.com/sqll/335551/ef-education-first-squareLogo-1731701655267.png",
                            "regularLogoUrl": "https://media.glassdoor.com/sql/335551/ef-education-first-squareLogo-1731701654832.png",
                            "shortName": "EF Education First"
                        },
                        "employerResponses": [],
                        "employmentStatus": "REGULAR",
                        "featured": false,
                        "flaggingDisabled": null,
                        "isCurrentJob": false,
                        "jobTitle": {
                            "__typename": "JobTitle",
                            "id": 15954,
                            "text": "Administrative Assistant"
                        },
                        "languageId": "eng",
                        "lengthOfEmployment": 4,
                        "location": {
                            "__typename": "City",
                            "id": 2671300,
                            "name": "London, England",
                            "type": "CITY"
                        },
                        "originalLanguageId": null,
                        "pros": "The company is big and the managing team is really supportive \nThere is a good atmosphere and I would have liked to stay more",
                        "prosOriginal": null,
                        "ratingBusinessOutlook": "NEUTRAL",
                        "ratingCareerOpportunities": 5.0,
                        "ratingCeo": "APPROVE",
                        "ratingCompensationAndBenefits": 5.0,
                        "ratingCultureAndValues": 5,
                        "ratingDiversityAndInclusion": 0,
                        "ratingOverall": 5,
                        "ratingRecommendToFriend": "POSITIVE",
                        "ratingSeniorLeadership": 5.0,
                        "ratingWorkLifeBalance": 5.0,
                        "relatedStructures": [],
                        "reviewDateTime": "2018-05-03T10:33:43.993",
                        "reviewId": 20420781,
                        "summary": "Former",
                        "summaryOriginal": null,
                        "translationMethod": null
                    },
                    {
                        "__typename": "EmployerReviewRG",
                        "advice": null,
                        "adviceOriginal": null,
                        "cons": "None i can think about, maybe at the beginning not a proper formation for employes, and the salary isn\u2019t that much",
                        "consOriginal": null,
                        "countHelpful": 0,
                        "countNotHelpful": 0,
                        "employer": {
                            "__typename": "Employer",
                            "id": 335551,
                            "largeLogoUrl": "https://media.glassdoor.com/sqll/335551/ef-education-first-squareLogo-1731701655267.png",
                            "regularLogoUrl": "https://media.glassdoor.com/sql/335551/ef-education-first-squareLogo-1731701654832.png",
                            "shortName": "EF Education First"
                        },
                        "employerResponses": [],
                        "employmentStatus": "REGULAR",
                        "featured": false,
                        "flaggingDisabled": null,
                        "isCurrentJob": false,
                        "jobTitle": {
                            "__typename": "JobTitle",
                            "id": 28220,
                            "text": "Sales Coordinator"
                        },
                        "languageId": "eng",
                        "lengthOfEmployment": 1,
                        "location": null,
                        "originalLanguageId": null,
                        "pros": "Very friendly company . Loved to work here, the offices are open space and the managers are always very keen on helping you",
                        "prosOriginal": null,
                        "ratingBusinessOutlook": "POSITIVE",
                        "ratingCareerOpportunities": 2.0,
                        "ratingCeo": "NO_OPINION",
                        "ratingCompensationAndBenefits": 3.0,
                        "ratingCultureAndValues": 5,
                        "ratingDiversityAndInclusion": 0,
                        "ratingOverall": 5,
                        "ratingRecommendToFriend": "POSITIVE",
                        "ratingSeniorLeadership": 5.0,
                        "ratingWorkLifeBalance": 2.0,
                        "relatedStructures": [],
                        "reviewDateTime": "2018-12-01T11:06:55.090",
                        "reviewId": 23653155,
                        "summary": "Sales coord\u00ednator",
                        "summaryOriginal": null,
                        "translationMethod": null
                    },
                    {
                        "__typename": "EmployerReviewRG",
                        "advice": "- Take the time to actually LISTEN to your employees and try to show empathy instead of listening just to respond.",
                        "adviceOriginal": null,
                        "cons": "- Managers tend to treat you like robots and work you to exhaustion.",
                        "consOriginal": null,
                        "countHelpful": 1,
                        "countNotHelpful": 0,
                        "employer": {
                            "__typename": "Employer",
                            "id": 335551,
                            "largeLogoUrl": "https://media.glassdoor.com/sqll/335551/ef-education-first-squareLogo-1731701655267.png",
                            "regularLogoUrl": "https://media.glassdoor.com/sql/335551/ef-education-first-squareLogo-1731701654832.png",
                            "shortName": "EF Education First"
                        },
                        "employerResponses": [],
                        "employmentStatus": "REGULAR",
                        "featured": false,
                        "flaggingDisabled": null,
                        "isCurrentJob": false,
                        "jobTitle": {
                            "__typename": "JobTitle",
                            "id": 42779,
                            "text": "ESL Teacher"
                        },
                        "languageId": "eng",
                        "lengthOfEmployment": 2,
                        "location": {
                            "__typename": "City",
                            "id": 2398510,
                            "name": "Beijing, Beijing",
                            "type": "CITY"
                        },
                        "originalLanguageId": null,
                        "pros": "- Many opportunities for progression",
                        "prosOriginal": null,
                        "ratingBusinessOutlook": null,
                        "ratingCareerOpportunities": 5.0,
                        "ratingCeo": null,
                        "ratingCompensationAndBenefits": 2.0,
                        "ratingCultureAndValues": 2,
                        "ratingDiversityAndInclusion": 0,
                        "ratingOverall": 3,
                        "ratingRecommendToFriend": null,
                        "ratingSeniorLeadership": 1.0,
                        "ratingWorkLifeBalance": 1.0,
                        "relatedStructures": [],
                        "reviewDateTime": "2020-01-11T12:49:41.763",
                        "reviewId": 31241534,
                        "summary": "Management and company culture needs improvement",
                        "summaryOriginal": null,
                        "translationMethod": null
                    }
                ]
            }
        }
    }
]